videosdk/plugins/nvidia/__init__.py
videosdk/plugins/nvidia/stt.py
videosdk/plugins/nvidia/tts.py
videosdk/plugins/nvidia/version.py
videosdk_plugins_nvidia-0.0.58.dist-info/METADATA
videosdk_plugins_nvidia-0.0.58.dist-info/WHEEL
videosdk_plugins_nvidia-0.0.58.dist-info/RECORD
