Metadata-Version: 2.4
Name: videosdk-plugins-nvidia
Version: 0.0.58
Summary: VideoSDK Agent Framework plugin for nvidia
Author: videosdk
License-Expression: Apache-2.0
Keywords: ai,audio,nvidia,riva,video,videosdk
Classifier: Development Status :: 4 - Beta
Classifier: Intended Audience :: Developers
Classifier: Topic :: Communications :: Conferencing
Classifier: Topic :: Multimedia :: Sound/Audio
Classifier: Topic :: Multimedia :: Video
Classifier: Topic :: Scientific/Engineering :: Artificial Intelligence
Requires-Python: >=3.11
Requires-Dist: nvidia-riva-client>=2.24.0
Requires-Dist: videosdk-agents>=0.0.58
